CmixAPIClient/__init__.py
CmixAPIClient/api.py
CmixAPIClient/error.py
CmixAPIClient/project.py
src/__init__.py
src/api.py
src/error.py
python_cmixapi_client-0.1.3.dist-info/LICENSE
python_cmixapi_client-0.1.3.dist-info/METADATA
python_cmixapi_client-0.1.3.dist-info/WHEEL
python_cmixapi_client-0.1.3.dist-info/top_level.txt
python_cmixapi_client-0.1.3.dist-info/RECORD
