Metadata-Version: 2.1
Name: python-cmixapi-client
Version: 0.1.3
Summary: A Python client for the Cmix API.
Home-page: https://github.com/dynata/python-cmixapi-client
Author: Bradley Wogsland
Author-email: bradley@wogsland.org
License: UNKNOWN
Keywords: cmix api dynata popresearch
Platform: Any
Classifier: Intended Audience :: Developers
Classifier: Operating System :: OS Independent
Classifier: Topic :: Software Development :: Libraries :: Python Modules
Classifier: Programming Language :: Python
Classifier: Programming Language :: Python :: 2
Classifier: Programming Language :: Python :: 2.7
Classifier: Programming Language :: Python :: 3
Classifier: Programming Language :: Python :: 3.6
Requires-Dist: requests
